audiobot/__init__.py
audiobot/cli.py
audiobot/config/__init__.py
audiobot/config/core.py
audiobot/core/__init__.py
audiobot/core/codec.py
audiobot/core/effects.py
audiobot/core/processor.py
audiobot/core/audio/core.py
audiobot/utils/logging_utils.py
audiobot/utils/metadata_utils.py
audiobot/utils/visualizer.py
filemac/__init__.py
filemac/cli/__init__.py
filemac/cli/converter.py
filemac/cli/main.py
filemac/core/__init__.py
filemac/core/document.py
filemac/core/exceptions.py
filemac/core/ocr.py
filemac/core/recorder.py
filemac/core/validator.py
filemac/core/warning.py
filemac/core/audio/core.py
filemac/core/audio/m4a_converter.py
filemac/core/image/core.py
filemac/core/image/extractor.py
filemac/core/pdf/core.py
filemac/core/svg/core.py
filemac/core/text/core.py
filemac/core/tts/core.py
filemac/core/tts/gtts.py
filemac/core/video/core.py
filemac/miscellaneous/VKITPro.py
filemac/miscellaneous/VRKit.py
filemac/miscellaneous/video_analyzer.py
filemac/utils/__init__.py
filemac/utils/colors.py
filemac/utils/config.py
filemac/utils/decorators.py
filemac/utils/file_utils.py
filemac/utils/formats.py
filemac/utils/helpmaster.py
filemac/utils/logging_utils.py
filemac/utils/screen.py
filemac/utils/simple.py
filemac/utils/security/vul_mitigate.py
filemac-2.0.1.dist-info/licenses/LICENSE
fweb/core/__init__.py
fweb/core/admin.py
fweb/core/apps.py
fweb/core/config.py
fweb/core/forms.py
fweb/core/models.py
fweb/core/tests.py
fweb/core/urls.py
fweb/core/utils.py
fweb/core/views.py
fweb/core/migrations/0001_initial.py
fweb/core/migrations/__init__.py
fweb/fweb/__init__.py
fweb/fweb/asgi.py
fweb/fweb/settings.py
fweb/fweb/urls.py
fweb/fweb/wsgi.py
voice/VoiceType.py
voice/__init__.py
filemac-2.0.1.dist-info/METADATA
filemac-2.0.1.dist-info/WHEEL
filemac-2.0.1.dist-info/entry_points.txt
filemac-2.0.1.dist-info/top_level.txt
filemac-2.0.1.dist-info/RECORD
