Metadata-Version: 2.4
Name: filemac
Version: 2.0.1
Summary: Open source Python CLI toolkit for conversion, manipulation, Analysis of files (All major file operations)
Home-page: https://pypi.org/project/filemac/
Author: wambua
Author-email: swskye17@gmail.com
License: GNU v3
Keywords: file-conversion,document-conversion,file-analysis,image-conversion,file-manipulation,audio-conversion,ocr,image-conversion,audio_effects,voice_shift,pdf,docx
Classifier: Environment :: Console
Classifier: Natural Language :: English
Classifier: Operating System :: OS Independent
Classifier: Programming Language :: Python
Classifier: Programming Language :: Python :: 3 :: Only
Classifier: Programming Language :: Python :: 3.11
Classifier: Programming Language :: Python :: 3.12
Classifier: Programming Language :: Python :: 3.13
Requires-Python: >=3.8
License-File: LICENSE
Requires-Dist: argparse
Requires-Dist: pdfminer.six
Requires-Dist: python-docx
Requires-Dist: python-pptx
Requires-Dist: gTTS
Requires-Dist: pypandoc
Requires-Dist: fitz
Requires-Dist: pydub
Requires-Dist: Pillow
Requires-Dist: pandas
Requires-Dist: opencv-python
Requires-Dist: pytesseract
Requires-Dist: PyPDF2
Requires-Dist: pdf2docx
Requires-Dist: requests
Requires-Dist: moviepy
Requires-Dist: reportlab
Requires-Dist: numpy
Requires-Dist: pdf2image
Requires-Dist: openpyxl
Requires-Dist: rich
Requires-Dist: tqdm
Requires-Dist: ffmpeg-python
Requires-Dist: librosa
Requires-Dist: python-magic
Requires-Dist: matplotlib
Requires-Dist: numpy
Requires-Dist: soundfile
Requires-Dist: SpeechRecognition
Requires-Dist: colorama
Requires-Dist: scipy
Requires-Dist: PyMuPDF
Requires-Dist: pyautogui
Requires-Dist: imageio
Requires-Dist: pynput
Requires-Dist: pyaudio
Requires-Dist: cairosvg
Dynamic: author
Dynamic: author-email
Dynamic: classifier
Dynamic: description
Dynamic: description-content-type
Dynamic: home-page
Dynamic: keywords
Dynamic: license
Dynamic: license-file
Dynamic: requires-dist
Dynamic: requires-python
Dynamic: summary
